chromesession/__init__.py
chromesession/chromium.py
chromesession/session.py
chromesession/utils.py
chromesession-0.1.3.dist-info/LICENSE
chromesession-0.1.3.dist-info/METADATA
chromesession-0.1.3.dist-info/WHEEL
chromesession-0.1.3.dist-info/RECORD
