Metadata-Version: 2.1
Name: chromesession
Version: 0.1.3
Summary: contextmanager for managing `selenium` chrome sessions with caching.
License: MIT
Keywords: selenium,requests-cache,chromedriver-py,responses
Author: Christoph Dörrer
Author-email: d-chris@web.de
Requires-Python: >=3.9,<4.0
Classifier: License :: OSI Approved :: MIT License
Classifier: Operating System :: OS Independent
Classifier: Programming Language :: Python :: 3
Classifier: Programming Language :: Python :: 3.9
Classifier: Programming Language :: Python :: 3.10
Classifier: Programming Language :: Python :: 3.11
Classifier: Programming Language :: Python :: 3.12
Classifier: Programming Language :: Python :: 3.13
Provides-Extra: all
Provides-Extra: bs4
Provides-Extra: driver
Requires-Dist: beautifulsoup4 (>=4.13.3) ; extra == "bs4" or extra == "all"
Requires-Dist: chromedriver-py (>=134.0.6998.88) ; extra == "driver" or extra == "all"
Requires-Dist: requests-cache (>=1.2.1)
Requires-Dist: responses (>=0.25.7)
Requires-Dist: selenium (>=4.29.0)
Project-URL: documentation, https://d-chris.github.io/chromesession
Project-URL: repository, https://github.com/d-chris/chromesession
